{"0":{"0":"時刻","1":"時","2":"1","3":"2","4":"3","5":"4","6":"5","7":"6","8":"7","9":"8","10":"9","11":"10","12":"11","13":"12","14":"13","15":"14","16":"15","17":"16","18":"17","19":"18","20":"19","21":"20","22":"21","23":"22","24":"23","25":"24"},"1":{"0":"気温","1":"℃","2":"9.5","3":"9.2","4":"9.4","5":"9.9","6":"9.8","7":"10.3","8":"12.8","9":"12.2","10":"12.0","11":"13.2","12":"14.2","13":"14.6","14":"14.9","15":"14.7","16":"13.9","17":null,"18":null,"19":null,"20":null,"21":null,"22":null,"23":null,"24":null,"25":null},"2":{"0":"降水量","1":"mm","2":"0.0","3":"0.0","4":"0.0","5":"0.0","6":"0.0","7":"0.0","8":"0.0","9":"0.0","10":"0.0","11":"0.0","12":"0.0","13":"0.0","14":"0.0","15":"0.0","16":"0.0","17":null,"18":null,"19":null,"20":null,"21":null,"22":null,"23":null,"24":null,"25":null},"3":{"0":"風向","1":"16方位","2":"南南西","3":"南","4":"南","5":"南南東","6":"南東","7":"南南東","8":"北西","9":"北北西","10":"南","11":"西","12":"北西","13":"北西","14":"北","15":"北北西","16":"北西","17":null,"18":null,"19":null,"20":null,"21":null,"22":null,"23":null,"24":null,"25":null},"4":{"0":"風速","1":"m\/s","2":"1.3","3":"2.0","4":"1.0","5":"2.1","6":"1.5","7":"2.1","8":"3.7","9":"2.7","10":"2.2","11":"0.7","12":"4.2","13":"4.0","14":"4.3","15":"5.3","16":"6.7","17":null,"18":null,"19":null,"20":null,"21":null,"22":null,"23":null,"24":null,"25":null},"5":{"0":"日照時間","1":"h","2":null,"3":null,"4":null,"5":"0.0","6":"0.0","7":"0.0","8":"0.0","9":"0.0","10":"0.0","11":"0.0","12":"0.0","13":"0.5","14":"0.6","15":"1.0","16":"0.9","17":null,"18":null,"19":null,"20":null,"21":null,"22":null,"23":null,"24":null,"25":null},"6":{"0":"積雪深","1":"cm","2":"0","3":"0","4":"0","5":"0","6":"0","7":"0","8":"0","9":"0","10":"0","11":"0","12":"0","13":"0","14":"0","15":"0","16":"0","17":null,"18":null,"19":null,"20":null,"21":null,"22":null,"23":null,"24":null,"25":null},"7":{"0":"湿度","1":"%","2":"81","3":"83","4":"80","5":"77","6":"77","7":"75","8":"63","9":"70","10":"70","11":"67","12":"56","13":"52","14":"53","15":"53","16":"51","17":null,"18":null,"19":null,"20":null,"21":null,"22":null,"23":null,"24":null,"25":null},"8":{"0":"気圧","1":"hPa","2":"1015.7","3":"1015.9","4":"1016.0","5":"1015.4","6":"1014.6","7":"1015.1","8":"1015.0","9":"1014.9","10":"1014.7","11":"1015.3","12":"1014.5","13":"1013.7","14":"1013.1","15":"1013.0","16":"1013.3","17":null,"18":null,"19":null,"20":null,"21":null,"22":null,"23":null,"24":null,"25":null}}